gather_tools/__init__.py
gather_tools/chorme.py
gather_tools/config.py
gather_tools/downloader.py
gather_tools/name.py
gather_tools-1.2.3.dist-info/METADATA
gather_tools-1.2.3.dist-info/WHEEL
gather_tools-1.2.3.dist-info/top_level.txt
gather_tools-1.2.3.dist-info/RECORD
